./.gitignore
./.python-version
./CODE_OF_CONDUCT.md
./CONTRIBUTING.md
./LICENSE
./PKG-INFO
./README.md
./SECURITY.md
./claude_desktop_config.json
./kubernetes_runbooks_server.py
./pyproject.toml
./uv.lock
./.github/workflows/dependency-updates.yml
./.github/workflows/main-checks.yml
./.github/workflows/publish-pypi.yml
./.github/workflows/pull-request-checks.yml
./.github/workflows/shared.yml
./.github/workflows/test-installation.yml
./src/create_mcp_server/__init__.py
./src/create_mcp_server/__main__.py
./src/create_mcp_server/template/README.md.jinja2
./src/create_mcp_server/template/__init__.py.jinja2
./src/create_mcp_server/template/kubernetes_runbooks_server.py.jinja2
./src/create_mcp_server/template/server.py.jinja2
kubernetes_runbooks_mcp_server-0.1.1.dist-info/METADATA
kubernetes_runbooks_mcp_server-0.1.1.dist-info/WHEEL
kubernetes_runbooks_mcp_server-0.1.1.dist-info/entry_points.txt
kubernetes_runbooks_mcp_server-0.1.1.dist-info/licenses/LICENSE
kubernetes_runbooks_mcp_server-0.1.1.dist-info/RECORD
