Metadata-Version: 2.4
Name: kubernetes-runbooks-mcp-server
Version: 0.1.1
Summary: A Model Context Protocol server that fetches Kubernetes troubleshooting runbooks
Project-URL: Homepage, https://github.com/raihan0824/kubernetes-runbooks-mcp-server
Project-URL: Repository, https://github.com/raihan0824/kubernetes-runbooks-mcp-server
Project-URL: Issues, https://github.com/raihan0824/kubernetes-runbooks-mcp-server/issues
Author-email: Raihan Afiandi <mraihanafiandi@gmail.com>
Maintainer-email: David Soria Parra <davidsp@anthropic.com>, Justin Spahr-Summers <justin@anthropic.com>
License: MIT
License-File: LICENSE
Classifier: Development Status :: 4 - Beta
Classifier: Intended Audience :: Developers
Classifier: License :: OSI Approved :: MIT License
Classifier: Programming Language :: Python :: 3
Classifier: Programming Language :: Python :: 3.10
Classifier: Programming Language :: Python :: 3.11
Classifier: Programming Language :: Python :: 3.12
Classifier: Topic :: Software Development :: Libraries :: Python Modules
Classifier: Topic :: System :: Systems Administration
Requires-Python: >=3.10
Requires-Dist: beautifulsoup4>=4.12.0
Requires-Dist: httpx>=0.27.0
Requires-Dist: lxml>=4.9.0
Requires-Dist: mcp>=1.0.0
